desync_search/__init__.py
desync_search/core.py
desync_search/data_structures.py
desync_search/tools.py
desync_search-0.2.29.dist-info/licenses/LICENSE
desync_search-0.2.29.dist-info/METADATA
desync_search-0.2.29.dist-info/WHEEL
desync_search-0.2.29.dist-info/top_level.txt
desync_search-0.2.29.dist-info/RECORD
