Metadata-Version: 2.4
Name: desync_search
Version: 0.2.29
Summary: API for the internet
Home-page: https://desync.ai
Author: Maksymilian Kubicki and Jackson Ballow
Author-email: maks@desync.ai and jackson@desync.ai
Classifier: Programming Language :: Python :: 3
Classifier: License :: OSI Approved :: MIT License
Classifier: Operating System :: OS Independent
Requires-Python: >=3.6
License-File: LICENSE
Requires-Dist: requests>=2.25.0
Dynamic: author
Dynamic: author-email
Dynamic: classifier
Dynamic: description
Dynamic: description-content-type
Dynamic: home-page
Dynamic: license-file
Dynamic: requires-dist
Dynamic: requires-python
Dynamic: summary
